{"trial_id": "03", "hyperparameters": {"space": [{"class_name": "Fixed", "config": {"name": "optimizer", "conditions": [], "value": "adam"}}, {"class_name": "Float", "config": {"name": "learning_rate", "default": 0.0001, "conditions": [], "min_value": 0.0001, "max_value": 0.01, "step": null, "sampling": "log"}}, {"class_name": "Float", "config": {"name": "beta_1", "default": 0.8, "conditions": [], "min_value": 0.8, "max_value": 0.99, "step": null, "sampling": "linear"}}, {"class_name": "Float", "config": {"name": "beta_2", "default": 0.9, "conditions": [], "min_value": 0.9, "max_value": 0.9999, "step": null, "sampling": "linear"}}, {"class_name": "Float", "config": {"name": "epsilon", "default": 1e-08, "conditions": [], "min_value": 1e-08, "max_value": 1e-06, "step": null, "sampling": "log"}}, {"class_name": "Boolean", "config": {"name": "amsgrad", "default": false, "conditions": []}}], "values": {"optimizer": "adam", "learning_rate": 0.0071223894490449685, "beta_1": 0.8978382112614723, "beta_2": 0.9087214185378951, "epsilon": 1.047217795168058e-07, "amsgrad": false}}, "metrics": {"metrics": {"accuracy": {"direction": "max", "observations": [{"value": [0.9703606367111206], "step": 7}]}, "loss": {"direction": "min", "observations": [{"value": [0.11401688307523727], "step": 7}]}, "val_accuracy": {"direction": "max", "observations": [{"value": [0.9776069521903992], "step": 7}]}, "val_loss": {"direction": "min", "observations": [{"value": [0.08332090079784393], "step": 7}]}}}, "score": 0.9776069521903992, "best_step": 7, "status": "COMPLETED", "message": null}